MANIFEST.in
setup.py
astrogear/__init__.py
astrogear/collaborate.py
astrogear/paths.py
astrogear/util.py
astrogear.egg-info/PKG-INFO
astrogear.egg-info/SOURCES.txt
astrogear.egg-info/dependency_links.txt
astrogear.egg-info/requires.txt
astrogear.egg-info/top_level.txt
astrogear/data/pysynphot-vega-fnu.xy
astrogear/data/icons/README.txt
astrogear/data/icons/add-files-to-archive.png
astrogear/data/icons/add-folder-to-archive.png
astrogear/data/icons/application-exit.png
astrogear/data/icons/appointment-new.png
astrogear/data/icons/bookmark-new.png
astrogear/data/icons/call-start.png
astrogear/data/icons/call-stop.png
astrogear/data/icons/contact-new.png
astrogear/data/icons/dialog-apply.png
astrogear/data/icons/dialog-ok.png
astrogear/data/icons/document-export.png
astrogear/data/icons/document-import.png
astrogear/data/icons/document-new.png
astrogear/data/icons/document-open-recent.png
astrogear/data/icons/document-open.png
astrogear/data/icons/document-page-setup.png
astrogear/data/icons/document-print-preview.png
astrogear/data/icons/document-print.png
astrogear/data/icons/document-properties.png
astrogear/data/icons/document-revert.png
astrogear/data/icons/document-save-as.png
astrogear/data/icons/document-save.png
astrogear/data/icons/document-send.png
astrogear/data/icons/edit-clear.png
astrogear/data/icons/edit-copy.png
astrogear/data/icons/edit-cut.png
astrogear/data/icons/edit-find-replace.png
astrogear/data/icons/edit-find.png
astrogear/data/icons/edit-paste.png
astrogear/data/icons/edit-redo.png
astrogear/data/icons/edit-select-all.png
astrogear/data/icons/edit-undo.png
astrogear/data/icons/extract-archive.png
astrogear/data/icons/folder-change.png
astrogear/data/icons/folder-copy.png
astrogear/data/icons/folder-move.png
astrogear/data/icons/folder-new.png
astrogear/data/icons/format-indent-less.png
astrogear/data/icons/format-indent-more.png
astrogear/data/icons/format-justify-center.png
astrogear/data/icons/format-justify-fill.png
astrogear/data/icons/format-justify-left.png
astrogear/data/icons/format-justify-right.png
astrogear/data/icons/format-text-bold.png
astrogear/data/icons/format-text-direction-ltr.png
