Metadata-Version: 1.0
Name: astrogear
Version: 0.17.1.11
Summary: Multi-purpose API to build Python applications born in Astronomical context
Home-page: https://github.com/trevisanj/astrogear
Author: Julio Trevisan
Author-email: juliotrevisan@gmail.com
License: GNU GPLv3
Keywords: astronomy,photometry,air-to-vacuum,vacuum-to-air,rainbow
Platform: any
